README.md
setup.py
pandas_parallel.egg-info/PKG-INFO
pandas_parallel.egg-info/SOURCES.txt
pandas_parallel.egg-info/dependency_links.txt
pandas_parallel.egg-info/not-zip-safe
pandas_parallel.egg-info/requires.txt
pandas_parallel.egg-info/top_level.txt
pd_parallel/__init__.py
pd_parallel/apply_parallel.py
pd_parallel/timeout.py
pd_parallel/tools.py
pd_parallel/utils.py